{
    "son_guncelleme": "21-06-2026 22:42",
    "canli_maclar": [
        {
            "lig": "FIFA World Cup",
            "ev": "Ecuador",
            "dep": "Curaçao",
            "skor": "0-0",
            "dakika": "YAKINDA",
            "ai_tahmini": "KG VAR",
            "ai_guven": "%85",
            "ai_analiz": "Form grafiklerine göre analiz edildi."
        },
        {
            "lig": "FIFA World Cup",
            "ev": "Tunisia",
            "dep": "Japan",
            "skor": "0-4",
            "dakika": "YAKINDA",
            "ai_tahmini": "MS 1",
            "ai_guven": "%85",
            "ai_analiz": "Form grafiklerine göre analiz edildi."
        },
        {
            "lig": "FIFA World Cup",
            "ev": "Spain",
            "dep": "Saudi Arabia",
            "skor": "4-0",
            "dakika": "YAKINDA",
            "ai_tahmini": "MS 1",
            "ai_guven": "%85",
            "ai_analiz": "Form grafiklerine göre analiz edildi."
        },
        {
            "lig": "FIFA World Cup",
            "ev": "Belgium",
            "dep": "Iran",
            "skor": "0-0",
            "dakika": "YAKINDA",
            "ai_tahmini": "KG VAR",
            "ai_guven": "%85",
            "ai_analiz": "Form grafiklerine göre analiz edildi."
        },
        {
            "lig": "FIFA World Cup",
            "ev": "Uruguay",
            "dep": "Cape Verde Islands",
            "skor": "0-1",
            "dakika": "CANLI",
            "ai_tahmini": "MS 2",
            "ai_guven": "%85",
            "ai_analiz": "Form grafiklerine göre analiz edildi."
        }
    ],
    "debug": "Football-Data Basarili"
}