{
    "son_guncelleme": "08-05-2026 16:05",
    "canli_maclar": [
        {
            "lig": "Copa Libertadores",
            "ev": "CD Coquimbo Unido",
            "dep": "Club Universitario de Deportes",
            "skor": "0-1",
            "dakika": "YAKINDA",
            "ai_tahmini": "MS 2",
            "ai_guven": "%85",
            "ai_analiz": "Form grafiklerine göre analiz edildi."
        },
        {
            "lig": "Copa Libertadores",
            "ev": "CD Independiente Medellín",
            "dep": "CR Flamengo",
            "skor": "0-0",
            "dakika": "CANLI",
            "ai_tahmini": "KG VAR",
            "ai_guven": "%85",
            "ai_analiz": "Form grafiklerine göre analiz edildi."
        },
        {
            "lig": "Copa Libertadores",
            "ev": "CDP Junior FC",
            "dep": "Club Cerro Porteño",
            "skor": "0-0",
            "dakika": "YAKINDA",
            "ai_tahmini": "MS 2",
            "ai_guven": "%85",
            "ai_analiz": "Form grafiklerine göre analiz edildi."
        },
        {
            "lig": "Bundesliga",
            "ev": "Borussia Dortmund",
            "dep": "Eintracht Frankfurt",
            "skor": "0-0",
            "dakika": "YAKINDA",
            "ai_tahmini": "KG VAR",
            "ai_guven": "%85",
            "ai_analiz": "Form grafiklerine göre analiz edildi."
        },
        {
            "lig": "Serie A",
            "ev": "Torino FC",
            "dep": "US Sassuolo Calcio",
            "skor": "0-0",
            "dakika": "YAKINDA",
            "ai_tahmini": "MS 1",
            "ai_guven": "%85",
            "ai_analiz": "Form grafiklerine göre analiz edildi."
        },
        {
            "lig": "Ligue 1",
            "ev": "Racing Club de Lens",
            "dep": "FC Nantes",
            "skor": "0-0",
            "dakika": "YAKINDA",
            "ai_tahmini": "MS 2",
            "ai_guven": "%85",
            "ai_analiz": "Form grafiklerine göre analiz edildi."
        },
        {
            "lig": "Primera Division",
            "ev": "Levante UD",
            "dep": "CA Osasuna",
            "skor": "0-0",
            "dakika": "YAKINDA",
            "ai_tahmini": "MS 1",
            "ai_guven": "%85",
            "ai_analiz": "Form grafiklerine göre analiz edildi."
        },
        {
            "lig": "Championship",
            "ev": "Hull City AFC",
            "dep": "Millwall FC",
            "skor": "0-0",
            "dakika": "YAKINDA",
            "ai_tahmini": "MS 1",
            "ai_guven": "%85",
            "ai_analiz": "Form grafiklerine göre analiz edildi."
        }
    ],
    "debug": "Football-Data Basarili"
}